{
  "type": "FeatureCollection",
  "features": [
    {
      "type": "Feature",
      "properties": {
        "Admin1": "Maharashtra",
        "Admin1_cur": "IND-MH",
        "Admin3": "Aurangabad",
        "Admin3_cur": "IND-MH-469",
        "Admin5": "Aurangabad",
        "Admin5_cur": "IND-MH-469-4312",
        "Admin7": "Abdimandi",
        "Admin7_hi": "अब्दीमंदी",
        "Admin7_lo": "अब्दीमंदी",
        "Admin7_cur": "IND-MH-469-4312-567069",
        "level_11": "Village",
        "pop_t_91": 1788,
        "Chri2001": 0,
        "Shape_Leng": 0.08379230168,
        "Shape_Area": 0.00035946134,
        "Category_N": null,
        "V_Code": 567069
      },
      "geometry": {
        "type": "MultiPolygon",
        "coordinates": [
          [
            [
              [
                75.2333532,
                19.9205482
              ],
              [
                75.2355294,
                19.9216089
              ],
              [
                75.2375329,
                19.9229216
              ],
              [
                75.240462,
                19.9247151
              ],
              [
                75.2440157,
                19.9263473
              ],
              [
                75.2447567,
                19.9268386
              ],
              [
                75.2448814,
                19.9285628
              ],
              [
                75.2451568,
                19.9303464
              ],
              [
                75.2457671,
                19.9316923
              ],
              [
                75.2466193,
                19.9323294
              ],
              [
                75.2475145,
                19.9325479
              ],
              [
                75.2491342,
                19.9326496
              ],
              [
                75.2527291,
                19.9324599
              ],
              [
                75.2494655,
                19.9374815
              ],
              [
                75.2432766,
                19.9478144
              ],
              [
                75.2421056,
                19.9499212
              ],
              [
                75.2337074,
                19.9501258
              ],
              [
                75.23297,
                19.9445409
              ],
              [
                75.2328647,
                19.9437434
              ],
              [
                75.2323904,
                19.9354117
              ],
              [
                75.2333532,
                19.9205482
              ]
            ]
          ]
        ]
      }
    },
    {
      "type": "Feature",
      "properties": {
        "Admin1": "Maharashtra",
        "Admin1_cur": "IND-MH",
        "Admin3": "Aurangabad",
        "Admin3_cur": "IND-MH-469",
        "Admin5": "Aurangabad",
        "Admin5_cur": "IND-MH-469-4312",
        "Admin7": "Satara Tanda",
        "Admin7_hi": "सातारा तांदा",
        "Admin7_lo": "सातारा तांदा",
        "Admin7_cur": "IND-MH-469-4312-803562",
        "level_11": "Village",
        "pop_t_91": 805,
        "Chri2001": 0,
        "Shape_Leng": 0.1023353985,
        "Shape_Area": 0.00055325185,
        "Category_N": null,
        "V_Code": 803562
      },
      "geometry": {
        "type": "MultiPolygon",
        "coordinates": [
          [
            [
              [
                75.3517316,
                19.800721
              ],
              [
                75.3521353,
                19.8018976
              ],
              [
                75.3521506,
                19.8029797
              ],
              [
                75.3523208,
                19.8035701
              ],
              [
                75.3526045,
                19.8039725
              ],
              [
                75.3528794,
                19.8042551
              ],
              [
                75.3531369,
                19.8042982
              ],
              [
                75.3536518,
                19.8043845
              ],
              [
                75.3544787,
                19.8043898
              ],
              [
                75.3550526,
                19.804412
              ],
              [
                75.3553777,
                19.8045108
              ],
              [
                75.3556395,
                19.8046138
              ],
              [
                75.3557377,
                19.8050886
              ],
              [
                75.3557007,
                19.8054521
              ],
              [
                75.3554062,
                19.8057725
              ],
              [
                75.3546818,
                19.8063018
              ],
              [
                75.3535822,
                19.8069162
              ],
              [
                75.3531109,
                19.8074287
              ],
              [
                75.3528971,
                19.8079844
              ],
              [
                75.352786,
                19.8108197
              ],
              [
                75.3532465,
                19.8127747
              ],
              [
                75.3541282,
                19.8144011
              ],
              [
                75.3548898,
                19.8152532
              ],
              [
                75.3556077,
                19.8155064
              ],
              [
                75.356199,
                19.8157681
              ],
              [
                75.3567991,
                19.8161495
              ],
              [
                75.3574036,
                19.8165908
              ],
              [
                75.3595246,
                19.817774
              ],
              [
                75.3583749,
                19.8203171
              ],
              [
                75.3576201,
                19.8221722
              ],
              [
                75.3560036,
                19.8270326
              ],
              [
                75.3554994,
                19.8262236
              ],
              [
                75.3547596,
                19.825671
              ],
              [
                75.3540962,
                19.8252937
              ],
              [
                75.3535223,
                19.8252716
              ],
              [
                75.3531382,
                19.8252368
              ],
              [
                75.3525098,
                19.8253386
              ],
              [
                75.3518268,
                19.8255644
              ],
              [
                75.3511612,
                19.8260296
              ],
              [
                75.3507576,
                19.8265979
              ],
              [
                75.3502906,
                19.8271703
              ],
              [
                75.3498738,
                19.8275589
              ],
              [
                75.3491908,
                19.8277846
              ],
              [
                75.3483179,
                19.8280229
              ],
              [
                75.3459677,
                19.8280582
              ],
              [
                75.3416164,
                19.8276842
              ],
              [
                75.339995,
                19.82725
              ],
              [
                75.3387818,
                19.8263074
              ],
              [
                75.3382057,
                19.8253828
              ],
              [
                75.3380224,
                19.8246127
              ],
              [
                75.3376646,
                19.8231924
              ],
              [
                75.3374268,
                19.8225463
              ],
              [
                75.3369358,
                19.8219169
              ],
              [
                75.3357401,
                19.8212138
              ],
              [
                75.3333573,
                19.8199273
              ],
              [
                75.3321354,
                19.8188649
              ],
              [
                75.3308285,
                19.8175073
              ],
              [
                75.3296416,
                19.815179
              ],
              [
                75.3279292,
                19.8099974
              ],
              [
                75.3271811,
                19.8075799
              ],
              [
                75.3310126,
                19.8060632
              ],
              [
                75.3392231,
                19.8044371
              ],
              [
                75.3469011,
                19.8024849
              ],
              [
                75.3517316,
                19.800721
              ]
            ]
          ]
        ]
      }
    },
    {
      "type": "Feature",
      "properties": {
        "Admin1": "Maharashtra",
        "Admin1_cur": "IND-MH",
        "Admin3": "Aurangabad",
        "Admin3_cur": "IND-MH-469",
        "Admin5": "Aurangabad",
        "Admin5_cur": "IND-MH-469-4312",
        "Admin7": "Garkheda",
        "Admin7_hi": "गार्खेदा",
        "Admin7_lo": "गार्खेदा",
        "Admin7_cur": "IND-MH-469-4312-332523",
        "level_11": "Village",
        "pop_t_91": 988,
        "Chri2001": 0,
        "Shape_Leng": 0.08232178744,
        "Shape_Area": 0.00039801126,
        "Category_N": null,
        "V_Code": 332523
      },
      "geometry": {
        "type": "MultiPolygon",
        "coordinates": [
          [
            [
              [
                75.5000945,
                19.8123127
              ],
              [
                75.501779,
                19.8101538
              ],
              [
                75.5035931,
                19.8088888
              ],
              [
                75.5057545,
                19.8080217
              ],
              [
                75.5073641,
                19.8074323
              ],
              [
                75.5104467,
                19.8069846
              ],
              [
                75.5150788,
                19.8068541
              ],
              [
                75.515842,
                19.806877
              ],
              [
                75.5194123,
                19.8069842
              ],
              [
                75.5209308,
                19.8068821
              ],
              [
                75.5224191,
                19.8066236
              ],
              [
                75.5214651,
                19.8123822
              ],
              [
                75.5200551,
                19.8216834
              ],
              [
                75.5188725,
                19.8237485
              ],
              [
                75.518627,
                19.8247278
              ],
              [
                75.5183183,
                19.8257113
              ],
              [
                75.5181772,
                19.8263827
              ],
              [
                75.5180671,
                19.8274732
              ],
              [
                75.5176773,
                19.8282215
              ],
              [
                75.5172831,
                19.8289098
              ],
              [
                75.5157454,
                19.8296149
              ],
              [
                75.5148651,
                19.8288917
              ],
              [
                75.5138128,
                19.8284208
              ],
              [
                75.5129092,
                19.8282408
              ],
              [
                75.5121498,
                19.8282918
              ],
              [
                75.5115259,
                19.828454
              ],
              [
                75.5106842,
                19.8291123
              ],
              [
                75.5098426,
                19.8297705
              ],
              [
                75.5084124,
                19.83107
              ],
              [
                75.5070512,
                19.8315825
              ],
              [
                75.5044288,
                19.8322399
              ],
              [
                75.5039375,
                19.8255937
              ],
              [
                75.5023352,
                19.8185406
              ],
              [
                75.5010365,
                19.8138741
              ],
              [
                75.5006493,
                19.8129373
              ],
              [
                75.5000945,
                19.8123127
              ]
            ]
          ]
        ]
      }
    },
    {
      "type": "Feature",
      "properties": {
        "Admin1": "Maharashtra",
        "Admin1_cur": "IND-MH",
        "Admin3": "Aurangabad",
        "Admin3_cur": "IND-MH-469",
        "Admin5": "Aurangabad",
        "Admin5_cur": "IND-MH-469-4312",
        "Admin7": "Nanakwadi",
        "Admin7_hi": "णनक्वदि",
        "Admin7_lo": "णनक्वदि",
        "Admin7_cur": "IND-MH-469-4312-610183",
        "level_11": "Village",
        "pop_t_91": 9,
        "Chri2001": 0,
        "Shape_Leng": 0.03389910606,
        "Shape_Area": 0.00008358475,
        "Category_N": null,
        "V_Code": 610183
      },
      "geometry": {
        "type": "MultiPolygon",
        "coordinates": [
          [
            [
              [
                75.3669156,
                19.9259948
              ],
              [
                75.3676709,
                19.9251739
              ],
              [
                75.3684422,
                19.9245721
              ],
              [
                75.3690516,
                19.9241462
              ],
              [
                75.3698229,
                19.9235445
              ],
              [
                75.3701925,
                19.9230244
              ],
              [
                75.3707,
                19.9219996
              ],
              [
                75.3710196,
                19.9215929
              ],
              [
                75.3714592,
                19.9212334
              ],
              [
                75.3724783,
                19.9208354
              ],
              [
                75.3732776,
                19.9206172
              ],
              [
                75.3736832,
                19.9205903
              ],
              [
                75.3745685,
                19.9207519
              ],
              [
                75.3749902,
                19.9209442
              ],
              [
                75.3755438,
                19.921348
              ],
              [
                75.3760555,
                19.9219749
              ],
              [
                75.3764553,
                19.9226642
              ],
              [
                75.3767932,
                19.9233026
              ],
              [
                75.3772291,
                19.9244851
              ],
              [
                75.377451,
                19.9251312
              ],
              [
                75.3776092,
                19.9264974
              ],
              [
                75.3776153,
                19.927378
              ],
              [
                75.3775395,
                19.9279337
              ],
              [
                75.3772898,
                19.9285009
              ],
              [
                75.3766505,
                19.9293143
              ],
              [
                75.3756394,
                19.9298218
              ],
              [
                75.3742226,
                19.9303563
              ],
              [
                75.3731954,
                19.9306447
              ],
              [
                75.3722801,
                19.9308705
              ],
              [
                75.371183,
                19.9309983
              ],
              [
                75.3700779,
                19.9310165
              ],
              [
                75.3687329,
                19.9309405
              ],
              [
                75.3680214,
                19.9307673
              ],
              [
                75.3675877,
                19.9304106
              ],
              [
                75.367064,
                19.9296193
              ],
              [
                75.3668899,
                19.928034
              ],
              [
                75.3668358,
                19.9264957
              ],
              [
                75.3669156,
                19.9259948
              ]
            ]
          ]
        ]
      }
    },
    {
      "type": "Feature",
      "properties": {
        "Admin1": "Maharashtra",
        "Admin1_cur": "IND-MH",
        "Admin3": "Aurangabad",
        "Admin3_cur": "IND-MH-469",
        "Admin5": "Aurangabad",
        "Admin5_cur": "IND-MH-469-4312",
        "Admin7": "Ibrahimpur",
        "Admin7_hi": "इब्रहिम्पुर",
        "Admin7_lo": "इब्रहिम्पुर",
        "Admin7_cur": "IND-MH-469-4312-470378",
        "level_11": "Village",
        "pop_t_91": 79,
        "Chri2001": 0,
        "Shape_Leng": 0.06354203542,
        "Shape_Area": 0.00022487118,
        "Category_N": null,
        "V_Code": 470378
      },
      "geometry": {
        "type": "MultiPolygon",
        "coordinates": [
          [
            [
              [
                75.5092158,
                19.7696999
              ],
              [
                75.5104442,
                19.7699784
              ],
              [
                75.5122685,
                19.770578
              ],
              [
                75.5152169,
                19.7717639
              ],
              [
                75.5170268,
                19.7730263
              ],
              [
                75.5200038,
                19.7763163
              ],
              [
                75.5217094,
                19.7778865
              ],
              [
                75.5249062,
                19.7824253
              ],
              [
                75.5287504,
                19.7862586
              ],
              [
                75.5268557,
                19.7872886
              ],
              [
                75.5253684,
                19.7878098
              ],
              [
                75.523637,
                19.7884678
              ],
              [
                75.5222762,
                19.7889804
              ],
              [
                75.5188998,
                19.7897489
              ],
              [
                75.5181318,
                19.7896802
              ],
              [
                75.5167267,
                19.7895941
              ],
              [
                75.5144314,
                19.7895076
              ],
              [
                75.513144,
                19.7892932
              ],
              [
                75.5113106,
                19.7885739
              ],
              [
                75.5092158,
                19.7696999
              ]
            ]
          ]
        ]
      }
    },
    {
      "type": "Feature",
      "properties": {
        "Admin1": "Maharashtra",
        "Admin1_cur": "IND-MH",
        "Admin3": "Aurangabad",
        "Admin3_cur": "IND-MH-469",
        "Admin5": "Aurangabad",
        "Admin5_cur": "IND-MH-469-4312",
        "Admin7": "Pandhari",
        "Admin7_hi": "पंधरी",
        "Admin7_lo": "पंधरी",
        "Admin7_cur": "IND-MH-469-4312-430338",
        "level_11": "Village",
        "pop_t_91": 814,
        "Chri2001": 0,
        "Shape_Leng": 0.06747377872,
        "Shape_Area": 0.00027021537,
        "Category_N": null,
        "V_Code": 430338
      },
      "geometry": {
        "type": "MultiPolygon",
        "coordinates": [
          [
            [
              [
                75.5101525,
                19.7196798
              ],
              [
                75.521538,
                19.716869
              ],
              [
                75.5257734,
                19.7318951
              ],
              [
                75.5245711,
                19.7319571
              ],
              [
                75.5212121,
                19.7323564
              ],
              [
                75.5179123,
                19.7323181
              ],
              [
                75.5147164,
                19.7324462
              ],
              [
                75.5121711,
                19.7327039
              ],
              [
                75.5100032,
                19.7331096
              ],
              [
                75.5064106,
                19.734145
              ],
              [
                75.5059262,
                19.7320718
              ],
              [
                75.5034747,
                19.7255572
              ],
              [
                75.5022783,
                19.7229353
              ],
              [
                75.507126,
                19.720427
              ],
              [
                75.5101525,
                19.7196798
              ]
            ]
          ]
        ]
      }
    }
  ]
}
